nitor_audit/cli.py
nitor_audit-0.1.2.data/scripts/audit.sh
nitor_audit-0.1.2.dist-info/LICENSE
nitor_audit-0.1.2.dist-info/METADATA
nitor_audit-0.1.2.dist-info/WHEEL
nitor_audit-0.1.2.dist-info/entry_points.txt
nitor_audit-0.1.2.dist-info/top_level.txt
nitor_audit-0.1.2.dist-info/RECORD
