Metadata-Version: 2.1
Name: nitor-audit
Version: 0.1.2
Summary: Tools for uploading security audit logs to a centralized sftp server
Home-page: http://github.com/NitorCreations/nitor-audit
Author: Pasi Niemi
Author-email: pasi.niemi@nitor.com
License: GPL 3.0
Download-URL: https://github.com/NitorCreations/nitor-audit/tarball/0.1
Platform: UNKNOWN
